Workbook

Sheet 0_Summary
A1: Cheerio Co-Pilot - Numbers at a glance
A2: All values below are live formulas linked to tabs 1-5. Change a blue cell anywhere and this updates.
A4: Monthly support queries | B4: ='1_Guesstimate_Volume'!B16 | C4: queries
A5: Resolved without a human | B5: ='1_Guesstimate_Volume'!B40 | C5: queries
A6: AI self-serve rate | B6: ='1_Guesstimate_Volume'!B36
A7: Still need a human | B7: ='1_Guesstimate_Volume'!B41 | C7: queries
A8: LLM cost per query | B8: ='2_AI_Running_Cost'!B27 | C8: ₹
A9: All-in cost per AI-resolved query | B9: ='2_AI_Running_Cost'!B36 | C9: ₹
A10: Monthly AI running cost | B10: ='2_AI_Running_Cost'!B34 | C10: ₹/mo
A11: Pro add-on revenue | B11: ='3_Billing_&_Margins'!B18 | C11: ₹/mo
A12: Pro add-on gross margin | B12: ='3_Billing_&_Margins'!B24
A13: Baseline human support cost | B13: ='4_Human_Savings_Comparison'!B11 | C13: ₹/mo
A14: New cost (humans + AI) | B14: ='4_Human_Savings_Comparison'!B21 | C14: ₹/mo
A15: Net monthly savings | B15: ='4_Human_Savings_Comparison'!B24 | C15: ₹/mo
A16: Net annual savings | B16: ='4_Human_Savings_Comparison'!B25 | C16: ₹/yr
A17: Cost reduction | B17: ='4_Human_Savings_Comparison'!B26
A18: Support agents: before -> after | B18: ='4_Human_Savings_Comparison'!B9&" -> "&'4_Human_Savings_Comparison'!B18 | C18: agents

Sheet 1_Guesstimate_Volume
A1: 1. Guesstimate - Monthly support volume | F1: Legend
A2: How many support queries 5,000 businesses raise per month, and how many Cheerio Co-Pilot resolves. | F2: Assumption (edit)
F3: Formula (do not edit)
F4: Key output
A5: Customer base | B5: Value | C5: Unit | D5: Logic / Source
A6: Active businesses | B6: 5000 | C6: businesses | D6: Given in brief
A7: Share onboarding this month (new / setting up) | B7: 0.15 | C7: % | D7: Assumption: ~15% of base is in first 30 days or re-configuring
A8: Onboarding businesses | B8: =B6*B7 | C8: businesses | D8: Calc: Active x Onboarding %
A9: Existing active businesses | B9: =B6-B8 | C9: businesses | D9: Calc: Active - Onboarding
A11: Tickets per business | B11: Value | C11: Unit | D11: Logic / Source
A12: Setup queries per onboarding business / month | B12: 4.2 | C12: queries | D12: Assumption: WABA setup, first templates, first flow, one integration
A13: Queries per existing business / month | B13: 1.4 | C13: queries | D13: Assumption: template rejections, delivery drops, flow edits
A14: Queries from onboarding businesses | B14: =B8*B12 | C14: queries/mo | D14: Calc: Onboarding biz x rate
A15: Queries from existing businesses | B15: =B9*B13 | C15: queries/mo | D15: Calc: Existing biz x rate
A16: TOTAL monthly support queries | B16: =B14+B15 | C16: queries/mo | D16: Calc: Sum of both segments
A18: Query mix (top issues) | B18: Value | C18: Unit | D18: Logic / Source
A19: WhatsApp template rejections & variable formatting - share | B19: 0.28 | C19: % | D19: Assumption (validate against helpdesk tags)
A20: Chatbot flow builder - broken nodes & limits - share | B20: 0.22 | C20: % | D20: Assumption (validate against helpdesk tags)
A21: WABA onboarding & number verification - share | B21: 0.18 | C21: % | D21: Assumption (validate against helpdesk tags)
A22: Campaign delivery - 24h window & tier limits - share | B22: 0.17 | C22: % | D22: Assumption (validate against helpdesk tags)
A23: Shopify / Zoho / webhook integration sync - share | B23: 0.1 | C23: % | D23: Assumption (validate against helpdesk tags)
A24: Billing, account bans, custom enterprise - share | B24: 0.05 | C24: % | D24: Assumption (validate against helpdesk tags)
A25: Mix check (must = 100%) | B25: =SUM(B19:B24) | C25: % | D25: Sanity check
A26: WhatsApp template rejections & variable formatting - queries | B26: =B16*B19 | C26: queries/mo | D26: Calc: Total x share
A27: Chatbot flow builder - broken nodes & limits - queries | B27: =B16*B20 | C27: queries/mo | D27: Calc: Total x share
A28: WABA onboarding & number verification - queries | B28: =B16*B21 | C28: queries/mo | D28: Calc: Total x share
A29: Campaign delivery - 24h window & tier limits - queries | B29: =B16*B22 | C29: queries/mo | D29: Calc: Total x share
A30: Shopify / Zoho / webhook integration sync - queries | B30: =B16*B23 | C30: queries/mo | D30: Calc: Total x share
A31: Billing, account bans, custom enterprise - queries | B31: =B16*B24 | C31: queries/mo | D31: Calc: Total x share
A33: Resolution funnel with Cheerio Co-Pilot | B33: Value | C33: Unit | D33: Logic / Source
A34: Tier 0 - proactive in-app auto-fix (before a ticket) | B34: 0.45 | C34: % of total | D34: Assumption: inline fix on the error screen (templates, flow lint)
A35: Tier 1 - guided AI diagnosis in Co-Pilot drawer | B35: 0.25 | C35: % of total | D35: Assumption: multi-step guidance (WABA, delivery, integrations)
A36: AI self-serve resolution rate | B36: =B34+B35 | C36: % | D36: Calc: Tier 0 + Tier 1
A37: Tier 2 - escalated to human (with diagnostic packet) | B37: =1-B36 | C37: % | D37: Calc: 1 - AI rate
A38: Resolved at Tier 0 | B38: =B16*B34 | C38: queries/mo
A39: Resolved at Tier 1 | B39: =B16*B35 | C39: queries/mo
A40: Resolved WITHOUT a human | B40: =B38+B39 | C40: queries/mo | D40: Calc: Tier 0 + Tier 1
A41: Still need a human | B41: =B16-B40 | C41: queries/mo | D41: Calc: Total - AI resolved

Sheet 2_AI_Running_Cost
A1: 2. AI running cost - per query and per month | F1: Legend
A2: Multi-turn token math. Prices: Anthropic API pricing (claude.com/pricing), checked Oct 2026. Edit blue cells to test other models. | F2: Assumption (edit)
F3: Formula (do not edit)
F4: Key output
A5: Model prices (USD per 1M tokens) | B5: Value | C5: Unit | D5: Logic / Source
A6: Fast model input - Claude Haiku 5.5 | B6: 0.1 | C6: $/1M | D6: Anthropic API pricing, prompts <=100K tokens. Used for triage + guided steps.
A7: Fast model output - Claude Haiku 5.5 | B7: 0.5 | C7: $/1M | D7: Anthropic API pricing
A8: Smart model input - Claude Sonnet 5.5 | B8: 2 | C8: $/1M | D8: Anthropic API pricing. Used for template rewrites + flow debugging.
A9: Smart model output - Claude Sonnet 5.5 | B9: 10 | C9: $/1M | D9: Anthropic API pricing
A10: Share of queries on fast model | B10: 0.8 | C10: % | D10: Assumption: router sends simple cases to Haiku
A11: Share of queries on smart model | B11: =1-B10 | C11: % | D11: Calc: 1 - fast share
A13: Tokens per query (multi-turn) | B13: Value | C13: Unit | D13: Logic / Source
A14: Average turns per session | B14: 3.5 | C14: turns | D14: Assumption: diagnose -> confirm -> fix -> verify
A15: Input tokens per turn | B15: 2800 | C15: tokens | D15: System prompt ~900 + page/error JSON ~600 + RAG chunk ~800 + history ~500
A16: Output tokens per turn | B16: 450 | C16: tokens | D16: Plain-English answer + JSON fix payload
A17: Input tokens per query | B17: =B14*B15 | C17: tokens | D17: Calc: turns x input/turn
A18: Output tokens per query | B18: =B14*B16 | C18: tokens | D18: Calc: turns x output/turn
A19: Retry / cache-miss buffer | B19: 0.15 | C19: % | D19: Assumption: failed tool calls, regenerations
A21: Cost per query | B21: Value | C21: Unit | D21: Logic / Source
A22: Fast-model cost per query | B22: =(B17*B6+B18*B7)/1000000 | C22: USD | D22: Calc: (in x price + out x price) / 1M
A23: Smart-model cost per query | B23: =(B17*B8+B18*B9)/1000000 | C23: USD | D23: Calc: (in x price + out x price) / 1M
A24: Blended cost per query (before buffer) | B24: =B10*B22+B11*B23 | C24: USD | D24: Calc: weighted by routing share
A25: LLM cost per query (with buffer) | B25: =B24*(1+B19) | C25: USD | D25: Calc: blended x (1 + buffer)
A26: FX rate | B26: 84 | C26: ₹ per $ | D26: Assumption - edit to today's rate
A27: LLM cost per query | B27: =B25*B26 | C27: ₹ | D27: Calc: USD x FX
A29: Monthly running cost | B29: Value | C29: Unit | D29: Logic / Source
A30: Queries hitting the AI per month | B30: ='1_Guesstimate_Volume'!B16 | C30: queries/mo | D30: From tab 1 - every query starts with Co-Pilot, incl. escalated ones
A31: LLM spend per month | B31: =B30*B25 | C31: USD | D31: Calc: volume x cost/query
A32: Fixed infra (vector DB + Langfuse logging + hosting) | B32: 120 | C32: USD/mo | D32: Assumption: Pinecone starter + Langfuse + small container
A33: Total AI running cost | B33: =B31+B32 | C33: USD/mo | D33: Calc: LLM + infra
A34: Total AI running cost | B34: =B33*B26 | C34: ₹/mo | D34: Calc: USD x FX
A35: All-in cost per query (LLM + infra) | B35: =B34/B30 | C35: ₹ | D35: Calc: monthly cost / all queries
A36: All-in cost per AI-RESOLVED query | B36: =B34/'1_Guesstimate_Volume'!B40 | C36: ₹ | D36: Calc: monthly cost / queries resolved without human (the honest unit)
A38: Sensitivity - what if we used a different model? | B38: Value | C38: Unit | D38: Logic / Source
A39: Alt: GPT-4o-mini input | B39: 0.15 | C39: $/1M | D39: OpenAI API pricing page - verify before relying on it
A40: Alt: GPT-4o-mini output | B40: 0.6 | C40: $/1M | D40: OpenAI API pricing page
A41: Alt: cost per query if 100% GPT-4o-mini | B41: =(B17*B39+B18*B40)/1000000*(1+B19)*B26 | C41: ₹ | D41: Same token math
A42: Worst case: cost per query if 100% Sonnet 5.5 | B42: =B23*(1+B19)*B26 | C42: ₹ | D42: If the router breaks and everything goes to the smart model

Sheet 3_Billing_&_Margins
A1: 3. Billing - how we charge and the margin | F1: Legend
A2: Recommendation: core setup help is FREE; a paid 'Co-Pilot Pro' add-on covers the cost many times over. | F2: Assumption (edit)
F3: Formula (do not edit)
F4: Key output
A5: Option comparison (qualitative) | B5: Value | C5: Unit | D5: Logic / Source
A6: Option | B6: Pro | D6: Con / Why
A7: A. Free, included in all plans | B7: Zero friction, max deflection | D7: No direct revenue; cost absorbed
A8: B. Per-conversation charge (e.g. ₹5/query) | B8: Revenue tracks usage | D8: Charges users exactly when they are stuck -> they go back to tickets. Rejected.
A9: C. AI credits pool | B9: Flexible, familiar from WhatsApp credits | D9: Users must budget for help; confusing for non-technical owners
A10: D. Plan add-on (flat monthly) | B10: Predictable revenue, easy to explain | D10: Must avoid paywalling basic setup help
A11: RECOMMENDED: Hybrid - Free core + Pro add-on | B11: Free setup fixes keep activation high; Pro monetises power users | D11: Need a fair-use cap on free tier
A13: Recommended pricing | B13: Value | C13: Unit | D13: Logic / Source
A14: Free auto-fixes per business / month | B14: 15 | C14: fixes | D14: Covers ~3x a typical business's monthly need (tab 1 rates)
A15: Co-Pilot Pro add-on price (Starter plan) | B15: 999 | C15: ₹/mo | D15: Unlimited template rewriter, auto-flow builder, priority audit. Bundled free in Growth/Enterprise.
A16: Attach rate (businesses buying Pro) | B16: 0.12 | C16: % | D16: Assumption: similar to other SaaS power-user add-ons
A17: Paying Pro businesses | B17: ='1_Guesstimate_Volume'!B6*B16 | C17: businesses | D17: Calc: Active x attach rate
A18: Monthly add-on revenue | B18: =B17*B15 | C18: ₹/mo | D18: Calc: buyers x price
A20: Margin | B20: Value | C20: Unit | D20: Logic / Source
A21: Total monthly AI running cost (ALL users, free + Pro) | B21: ='2_AI_Running_Cost'!B34 | C21: ₹/mo | D21: From tab 2 - conservative: Pro revenue carries everyone's AI cost
A22: Extra cost of Pro usage (heavy users) | B22: =B17*20*'2_AI_Running_Cost'!B27*2 | C22: ₹/mo | D22: Assumption: each Pro user runs 20 extra sessions/mo at 2x tokens
A23: Gross profit | B23: =B18-B21-B22 | C23: ₹/mo | D23: Calc: revenue - costs
A24: Gross margin | B24: =B23/B18 | C24: % | D24: Calc: profit / revenue
A25: Break-even Pro buyers | B25: =CEILING((B21+B22)/B15,1) | C25: businesses | D25: Buyers needed to cover all AI cost
A26: AI cost per business per month (all tenants) | B26: =B21/'1_Guesstimate_Volume'!B6 | C26: ₹/biz/mo | D26: Even at 0% attach, this is tiny vs. plan prices

Sheet 4_Human_Savings_Comparison
A1: 4. Savings - Co-Pilot vs. 100% human support | F1: Legend
A2: Same monthly volume, two ways of handling it. | F2: Assumption (edit)
F3: Formula (do not edit)
F4: Key output
A5: Baseline: every query handled by a human | B5: Value | C5: Unit | D5: Logic / Source
A6: Average handling time per setup ticket | B6: 18 | C6: minutes | D6: Assumption: screenshot back-and-forth, checking Meta errors
A7: Productive hours per agent / month | B7: 160 | C7: hours | D7: Assumption: 8h x 20 days
A8: Tickets per agent per month | B8: =(B7*60)/B6 | C8: tickets | D8: Calc: minutes available / AHT
A9: Agents needed | B9: =CEILING('1_Guesstimate_Volume'!B16/B8,1) | C9: agents | D9: Calc: volume / capacity, rounded up
A10: Fully loaded cost per L1/L2 agent (India) | B10: 35000 | C10: ₹/mo | D10: Assumption: salary + PF + tools + mgmt overhead
A11: Baseline monthly support cost | B11: =B9*B10 | C11: ₹/mo | D11: Calc: agents x cost
A12: Baseline cost per ticket | B12: =B11/'1_Guesstimate_Volume'!B16 | C12: ₹
A14: With Cheerio Co-Pilot | B14: Value | C14: Unit | D14: Logic / Source
A15: Tickets still reaching humans | B15: ='1_Guesstimate_Volume'!B41 | C15: tickets/mo | D15: From tab 1
A16: New AHT (diagnostic packet pre-attached) | B16: 10 | C16: minutes | D16: Assumption: WABA ID, error logs, steps tried arrive with the ticket, so no screenshot back-and-forth
A17: Tickets per agent per month | B17: =(B7*60)/B16 | C17: tickets | D17: Calc: minutes / new AHT
A18: Agents needed | B18: =CEILING(B15/B17,1) | C18: agents | D18: Rounded up
A19: Human cost | B19: =B18*B10 | C19: ₹/mo
A20: AI running cost | B20: ='2_AI_Running_Cost'!B34 | C20: ₹/mo | D20: From tab 2
A21: Total new monthly cost | B21: =B19+B20 | C21: ₹/mo | D21: Calc: human + AI
A23: Savings | B23: Value | C23: Unit | D23: Logic / Source
A24: Net monthly savings | B24: =B11-B21 | C24: ₹/mo | D24: Calc: baseline - new
A25: Net annual savings | B25: =B24*12 | C25: ₹/yr
A26: Cost reduction | B26: =B24/B11 | C26: %
A27: Support hires avoided at today's scale | B27: =B9-B18 | C27: agents
A28: If customers double: baseline agents | B28: =CEILING('1_Guesstimate_Volume'!B16*2/B8,1) | C28: agents | D28: Shows the scaling problem from the brief
A29: If customers double: agents with Co-Pilot | B29: =CEILING(B15*2/B17,1) | C29: agents

Sheet 5_Monthly_Audit_&_Alerts
A1: 5. Monthly audit - checks and alerts that keep Co-Pilot profitable and honest
A2: Column C = this month's value (formula or sample input). Column E = live status formula. Wire the same rules into Metabase/Grafana + Slack.
A4: Check | B4: What it catches | C4: This month (sample) | D4: Threshold | E4: Status | F4: Owner / cadence | G4: Action if breached
A5: LLM cost per query (₹) | B5: Prompt bloat, retry loops, router sending too much to Sonnet | C5: ='2_AI_Running_Cost'!B27 | D5: 2 | E5: =IF(C5>D5,"ALERT","OK") | F5: Eng - daily | G5: Check router share + prompt size in Langfuse; roll back last prompt change
A6: All-in cost per AI-resolved query (₹) | B6: Cost rising faster than resolutions | C6: ='2_AI_Running_Cost'!B36 | D6: 4 | E6: =IF(C6>D6,"ALERT","OK") | F6: PM - weekly | G6: Investigate low-resolution intents; cut turns or add deterministic fixes
A7: Monthly AI spend vs. budget (₹) | B7: Overall bill drift | C7: ='2_AI_Running_Cost'!B34 | D7: 25000 | E7: =IF(C7>D7,"ALERT","OK") | F7: PM + Finance - monthly | G7: Freeze new intents until root cause found
A8: Max spend by one tenant (₹/mo) | B8: Loops / abuse by a single business (cap ₹150 or 50 sessions/day) | C8: 45 | D8: 150 | E8: =IF(C8>D8,"ALERT","OK") | F8: Auto - real time | G8: Auto-throttle tenant to rule-based diagnostics; notify CSM
A9: Ghost re-open rate | B9: AI said 'solved' but user raised a human ticket within 24h | C9: 0.08 | D9: 0.12 | E9: =IF(C9>D9,"ALERT","OK") | F9: PM - weekly | G9: Pull the intents with highest re-open; fix prompts/playbooks
A10: Hallucination rate (50-chat weekly audit) | B10: Wrong Meta policy advice, invented fixes | C10: 0.006 | D10: 0.01 | E10: =IF(C10>D10,"ALERT","OK") | F10: PM + LLM-judge - weekly | G10: Block that intent from auto-fix; add doc to RAG; re-test
A11: AI self-serve resolution rate | B11: Deflection falling below plan | C11: ='1_Guesstimate_Volume'!B36 | D11: 0.6 | E11: =IF(C11<D11,"ALERT","OK") | F11: PM - weekly | G11: Review top escalation reasons; add new auto-fix
A12: Pro add-on gross margin | B12: Pricing no longer covers cost | C12: ='3_Billing_&_Margins'!B24 | D12: 0.8 | E12: =IF(C12<D12,"ALERT","OK") | F12: Finance - monthly | G12: Revisit free-fix cap or Pro price
A13: Billing reconciliation gap | B13: Pro users billed vs. Pro entitlements active | C13: 0 | D13: 0.005 | E13: =IF(C13>D13,"ALERT","OK") | F13: Finance - monthly | G13: Fix entitlement sync; refund/charge diff
A15: Alerts firing this month | C15: =COUNTIF(E5:E13,"ALERT")
A17: Monthly audit ritual (1st working day)
A18: 1. Export usage by tenant from Langfuse -> compare tokens billed by Anthropic invoice vs. our logs (gap > 2% = investigate).
A19: 2. Run this sheet with last month's actuals in column C; every ALERT gets an owner + date in the PM review.
A20: 3. Sample 50 conversations: LLM-as-judge scores them for Meta-policy accuracy, then PM spot-checks 10 by hand.
A21: 4. Check top 10 tenants by spend: are they Pro payers? If a free tenant is in the top 10, review the fair-use cap.
